{"is_source_file": false, "format": "", "description": "", "external_files": [], "external_methods": [], "published": [], "classes": [], "methods": [], "calls": [], "search-terms": [], "state": 2, "file_id": 7, "knowledge_revision": 10, "git_revision": "dcfdba088be4161984141530b790b29f26dafb65", "hash": "bd6563ba91b6e0cb6b0269162808fa82", "format-version": 4, "code-base-name": "language_learning_database", "filename": "README.md", "revision_history": [{"10": "dcfdba088be4161984141530b790b29f26dafb65"}]}